[
  {
    "scraped_at": "2026-04-16T21:43:54+00:00",
    "source_url": "https://www.starmakerstudios.com/en/playlist/starmaker-top-songs/294",
    "source_name": "playlist",
    "song_title": "John Legend",
    "artist": "Points",
    "recordings_raw": "792K recordings",
    "recordings_num": 792000
  },
  {
    "scraped_at": "2026-04-16T21:43:54+00:00",
    "source_url": "https://www.starmakerstudios.com/en/playlist/starmaker-top-songs/294",
    "source_name": "playlist",
    "song_title": "Ed Sheeran",
    "artist": "Points",
    "recordings_raw": "660K recordings",
    "recordings_num": 660000
  },
  {
    "scraped_at": "2026-04-16T21:43:54+00:00",
    "source_url": "https://www.starmakerstudios.com/en/playlist/starmaker-top-songs/294",
    "source_name": "playlist",
    "song_title": "Ellie Goulding",
    "artist": "Points",
    "recordings_raw": "402K recordings",
    "recordings_num": 402000
  },
  {
    "scraped_at": "2026-04-16T21:43:54+00:00",
    "source_url": "https://www.starmakerstudios.com/en/playlist/starmaker-top-songs/294",
    "source_name": "playlist",
    "song_title": "Charlie Puth",
    "artist": "Points",
    "recordings_raw": "348K recordings",
    "recordings_num": 348000
  },
  {
    "scraped_at": "2026-04-16T21:43:54+00:00",
    "source_url": "https://www.starmakerstudios.com/en/playlist/starmaker-top-songs/294",
    "source_name": "playlist",
    "song_title": "Shawn Mendes",
    "artist": "Points",
    "recordings_raw": "228K recordings",
    "recordings_num": 228000
  },
  {
    "scraped_at": "2026-04-16T21:43:55+00:00",
    "source_url": "https://www.starmakerstudios.com/en/songs",
    "source_name": "songs",
    "song_title": "The Carpenters",
    "artist": "Points",
    "recordings_raw": "218K recordings",
    "recordings_num": 218000
  },
  {
    "scraped_at": "2026-04-16T21:43:54+00:00",
    "source_url": "https://www.starmakerstudios.com/en/playlist/starmaker-top-songs/294",
    "source_name": "playlist",
    "song_title": "Bruno Mars",
    "artist": "Points",
    "recordings_raw": "164K recordings",
    "recordings_num": 164000
  },
  {
    "scraped_at": "2026-04-16T21:43:54+00:00",
    "source_url": "https://www.starmakerstudios.com/en/playlist/starmaker-top-songs/294",
    "source_name": "playlist",
    "song_title": "Lewis Capaldi",
    "artist": "Points",
    "recordings_raw": "154K recordings",
    "recordings_num": 154000
  },
  {
    "scraped_at": "2026-04-16T21:43:55+00:00",
    "source_url": "https://www.starmakerstudios.com/en/songs",
    "source_name": "songs",
    "song_title": "Rex Smith",
    "artist": "Points",
    "recordings_raw": "107K recordings",
    "recordings_num": 107000
  },
  {
    "scraped_at": "2026-04-16T21:43:54+00:00",
    "source_url": "https://www.starmakerstudios.com/en/playlist/starmaker-top-songs/294",
    "source_name": "playlist",
    "song_title": "Hozier",
    "artist": "Points",
    "recordings_raw": "80K recordings",
    "recordings_num": 80000
  },
  {
    "scraped_at": "2026-04-16T21:43:55+00:00",
    "source_url": "https://www.starmakerstudios.com/en/songs",
    "source_name": "songs",
    "song_title": "REO Speedwagon",
    "artist": "Points",
    "recordings_raw": "79K recordings",
    "recordings_num": 79000
  },
  {
    "scraped_at": "2026-04-16T21:43:54+00:00",
    "source_url": "https://www.starmakerstudios.com/en/playlist/starmaker-top-songs/294",
    "source_name": "playlist",
    "song_title": "Billie Eilish",
    "artist": "Points",
    "recordings_raw": "74K recordings",
    "recordings_num": 74000
  },
  {
    "scraped_at": "2026-04-16T21:43:55+00:00",
    "source_url": "https://www.starmakerstudios.com/en/songs",
    "source_name": "songs",
    "song_title": "Barbra Streisand",
    "artist": "Points",
    "recordings_raw": "59K recordings",
    "recordings_num": 59000
  },
  {
    "scraped_at": "2026-04-16T21:43:55+00:00",
    "source_url": "https://www.starmakerstudios.com/en/songs",
    "source_name": "songs",
    "song_title": "R.E.M.",
    "artist": "Points",
    "recordings_raw": "55K recordings",
    "recordings_num": 55000
  },
  {
    "scraped_at": "2026-04-16T21:43:55+00:00",
    "source_url": "https://www.starmakerstudios.com/en/songs",
    "source_name": "songs",
    "song_title": "Keith Whitley",
    "artist": "Points",
    "recordings_raw": "34K recordings",
    "recordings_num": 34000
  },
  {
    "scraped_at": "2026-04-16T21:43:55+00:00",
    "source_url": "https://www.starmakerstudios.com/en/songs",
    "source_name": "songs",
    "song_title": "Bread",
    "artist": "Points",
    "recordings_raw": "21K recordings",
    "recordings_num": 21000
  },
  {
    "scraped_at": "2026-04-16T21:43:55+00:00",
    "source_url": "https://www.starmakerstudios.com/en/songs",
    "source_name": "songs",
    "song_title": "Paul Davis",
    "artist": "Points",
    "recordings_raw": "16K recordings",
    "recordings_num": 16000
  },
  {
    "scraped_at": "2026-04-16T21:43:55+00:00",
    "source_url": "https://www.starmakerstudios.com/en/songs",
    "source_name": "songs",
    "song_title": "Ronnie Milsap",
    "artist": "Points",
    "recordings_raw": "14K recordings",
    "recordings_num": 14000
  },
  {
    "scraped_at": "2026-04-16T21:43:55+00:00",
    "source_url": "https://www.starmakerstudios.com/en/songs",
    "source_name": "songs",
    "song_title": "Elvis Presley",
    "artist": "Points",
    "recordings_raw": "9K recordings",
    "recordings_num": 9000
  },
  {
    "scraped_at": "2026-04-16T21:43:56+00:00",
    "source_url": "https://www.starmakerstudios.com/playlist/%E6%9C%AC%E5%91%A8us%E7%86%B1%E9%96%80100/1357",
    "source_name": "playlist",
    "song_title": "djo",
    "artist": "Points",
    "recordings_raw": "9K recordings",
    "recordings_num": 9000
  },
  {
    "scraped_at": "2026-04-16T21:43:56+00:00",
    "source_url": "https://www.starmakerstudios.com/playlist/%E6%9C%AC%E5%91%A8us%E7%86%B1%E9%96%80100/1357",
    "source_name": "playlist",
    "song_title": "Bts",
    "artist": "Points",
    "recordings_raw": "3K recordings",
    "recordings_num": 3000
  },
  {
    "scraped_at": "2026-04-16T21:43:55+00:00",
    "source_url": "https://www.starmakerstudios.com/en/songs",
    "source_name": "songs",
    "song_title": "bruno mars",
    "artist": "DIE WITH A SMILE HD",
    "recordings_raw": "864 recordings",
    "recordings_num": 864
  },
  {
    "scraped_at": "2026-04-16T21:43:56+00:00",
    "source_url": "https://www.starmakerstudios.com/playlist/%E6%9C%AC%E5%91%A8us%E7%86%B1%E9%96%80100/1357",
    "source_name": "playlist",
    "song_title": "Kendrick Lamar/SZA",
    "artist": "Points",
    "recordings_raw": "851 recordings",
    "recordings_num": 851
  },
  {
    "scraped_at": "2026-04-16T21:43:55+00:00",
    "source_url": "https://www.starmakerstudios.com/en/songs",
    "source_name": "songs",
    "song_title": "Nightbirde",
    "artist": "It's OK",
    "recordings_raw": "616 recordings",
    "recordings_num": 616
  },
  {
    "scraped_at": "2026-04-16T21:43:56+00:00",
    "source_url": "https://www.starmakerstudios.com/playlist/%E6%9C%AC%E5%91%A8us%E7%86%B1%E9%96%80100/1357",
    "source_name": "playlist",
    "song_title": "Tame Impala",
    "artist": "Points",
    "recordings_raw": "540 recordings",
    "recordings_num": 540
  },
  {
    "scraped_at": "2026-04-16T21:43:55+00:00",
    "source_url": "https://www.starmakerstudios.com/en/songs",
    "source_name": "songs",
    "song_title": "Cali Swag District",
    "artist": "Points",
    "recordings_raw": "207 recordings",
    "recordings_num": 207
  },
  {
    "scraped_at": "2026-04-16T21:43:55+00:00",
    "source_url": "https://www.starmakerstudios.com/en/songs",
    "source_name": "songs",
    "song_title": "Miley Cyrus",
    "artist": "Points",
    "recordings_raw": "202 recordings",
    "recordings_num": 202
  },
  {
    "scraped_at": "2026-04-16T21:43:55+00:00",
    "source_url": "https://www.starmakerstudios.com/en/songs",
    "source_name": "songs",
    "song_title": "Jax",
    "artist": "Points",
    "recordings_raw": "165 recordings",
    "recordings_num": 165
  },
  {
    "scraped_at": "2026-04-16T21:43:55+00:00",
    "source_url": "https://www.starmakerstudios.com/en/songs",
    "source_name": "songs",
    "song_title": "The McClain Sisters",
    "artist": "The Great Divide",
    "recordings_raw": "118 recordings",
    "recordings_num": 118
  },
  {
    "scraped_at": "2026-04-16T21:43:56+00:00",
    "source_url": "https://www.starmakerstudios.com/playlist/%E6%9C%AC%E5%91%A8us%E7%86%B1%E9%96%80100/1357",
    "source_name": "playlist",
    "song_title": "Lil Uzi Vert",
    "artist": "Points",
    "recordings_raw": "73 recordings",
    "recordings_num": 73
  },
  {
    "scraped_at": "2026-04-16T21:43:56+00:00",
    "source_url": "https://www.starmakerstudios.com/playlist/%E6%9C%AC%E5%91%A8us%E7%86%B1%E9%96%80100/1357",
    "source_name": "playlist",
    "song_title": "RAYE/Hans Zimmer",
    "artist": "Points",
    "recordings_raw": "22 recordings",
    "recordings_num": 22
  },
  {
    "scraped_at": "2026-04-16T21:43:56+00:00",
    "source_url": "https://www.starmakerstudios.com/playlist/%E6%9C%AC%E5%91%A8us%E7%86%B1%E9%96%80100/1357",
    "source_name": "playlist",
    "song_title": "Noah Kahan",
    "artist": "Points",
    "recordings_raw": "12 recordings",
    "recordings_num": 12
  },
  {
    "scraped_at": "2026-04-16T21:43:56+00:00",
    "source_url": "https://www.starmakerstudios.com/playlist/%E6%9C%AC%E5%91%A8us%E7%86%B1%E9%96%80100/1357",
    "source_name": "playlist",
    "song_title": "Omar Courtz",
    "artist": "Points",
    "recordings_raw": "12 recordings",
    "recordings_num": 12
  },
  {
    "scraped_at": "2026-04-16T21:43:55+00:00",
    "source_url": "https://www.starmakerstudios.com/en/songs",
    "source_name": "songs",
    "song_title": "BLACKPINK",
    "artist": "Don't know what to do [English ver]",
    "recordings_raw": "10 recordings",
    "recordings_num": 10
  },
  {
    "scraped_at": "2026-04-16T21:43:56+00:00",
    "source_url": "https://www.starmakerstudios.com/playlist/%E6%9C%AC%E5%91%A8us%E7%86%B1%E9%96%80100/1357",
    "source_name": "playlist",
    "song_title": "Kanye West/Ye/Travis Scott",
    "artist": "Points",
    "recordings_raw": "4 recordings",
    "recordings_num": 4
  },
  {
    "scraped_at": "2026-04-16T21:43:56+00:00",
    "source_url": "https://www.starmakerstudios.com/playlist/%E6%9C%AC%E5%91%A8us%E7%86%B1%E9%96%80100/1357",
    "source_name": "playlist",
    "song_title": "Sam Fender/Olivia Dean",
    "artist": "Points",
    "recordings_raw": "2 recordings",
    "recordings_num": 2
  }
]