[
  {
    "scraped_at": "2026-07-21T20:18:24+00:00",
    "source_url": "https://www.starmakerstudios.com/en/playlist/starmaker-top-songs/294",
    "source_name": "playlist",
    "song_title": "John Legend",
    "artist": "Points",
    "recordings_raw": "795K recordings",
    "recordings_num": 795000
  },
  {
    "scraped_at": "2026-07-21T20:18:24+00:00",
    "source_url": "https://www.starmakerstudios.com/en/playlist/starmaker-top-songs/294",
    "source_name": "playlist",
    "song_title": "Ed Sheeran",
    "artist": "Points",
    "recordings_raw": "662K recordings",
    "recordings_num": 662000
  },
  {
    "scraped_at": "2026-07-21T20:18:24+00:00",
    "source_url": "https://www.starmakerstudios.com/en/playlist/starmaker-top-songs/294",
    "source_name": "playlist",
    "song_title": "Ellie Goulding",
    "artist": "Points",
    "recordings_raw": "404K recordings",
    "recordings_num": 404000
  },
  {
    "scraped_at": "2026-07-21T20:18:24+00:00",
    "source_url": "https://www.starmakerstudios.com/en/playlist/starmaker-top-songs/294",
    "source_name": "playlist",
    "song_title": "Charlie Puth",
    "artist": "Points",
    "recordings_raw": "348K recordings",
    "recordings_num": 348000
  },
  {
    "scraped_at": "2026-07-21T20:18:24+00:00",
    "source_url": "https://www.starmakerstudios.com/en/playlist/starmaker-top-songs/294",
    "source_name": "playlist",
    "song_title": "Shawn Mendes",
    "artist": "Points",
    "recordings_raw": "228K recordings",
    "recordings_num": 228000
  },
  {
    "scraped_at": "2026-07-21T20:18:25+00:00",
    "source_url": "https://www.starmakerstudios.com/en/songs",
    "source_name": "songs",
    "song_title": "Udit Narayan",
    "artist": "Points",
    "recordings_raw": "173K recordings",
    "recordings_num": 173000
  },
  {
    "scraped_at": "2026-07-21T20:18:24+00:00",
    "source_url": "https://www.starmakerstudios.com/en/playlist/starmaker-top-songs/294",
    "source_name": "playlist",
    "song_title": "Bruno Mars",
    "artist": "Points",
    "recordings_raw": "165K recordings",
    "recordings_num": 165000
  },
  {
    "scraped_at": "2026-07-21T20:18:24+00:00",
    "source_url": "https://www.starmakerstudios.com/en/playlist/starmaker-top-songs/294",
    "source_name": "playlist",
    "song_title": "Lewis Capaldi",
    "artist": "Points",
    "recordings_raw": "154K recordings",
    "recordings_num": 154000
  },
  {
    "scraped_at": "2026-07-21T20:18:25+00:00",
    "source_url": "https://www.starmakerstudios.com/en/songs",
    "source_name": "songs",
    "song_title": "Air Supply",
    "artist": "Points",
    "recordings_raw": "128K recordings",
    "recordings_num": 128000
  },
  {
    "scraped_at": "2026-07-21T20:18:25+00:00",
    "source_url": "https://www.starmakerstudios.com/en/songs",
    "source_name": "songs",
    "song_title": "Tommy Shaw",
    "artist": "Points",
    "recordings_raw": "127K recordings",
    "recordings_num": 127000
  },
  {
    "scraped_at": "2026-07-21T20:18:25+00:00",
    "source_url": "https://www.starmakerstudios.com/en/songs",
    "source_name": "songs",
    "song_title": "Nick Carter",
    "artist": "Points",
    "recordings_raw": "108K recordings",
    "recordings_num": 108000
  },
  {
    "scraped_at": "2026-07-21T20:18:24+00:00",
    "source_url": "https://www.starmakerstudios.com/en/playlist/starmaker-top-songs/294",
    "source_name": "playlist",
    "song_title": "Hozier",
    "artist": "Points",
    "recordings_raw": "80K recordings",
    "recordings_num": 80000
  },
  {
    "scraped_at": "2026-07-21T20:18:24+00:00",
    "source_url": "https://www.starmakerstudios.com/en/playlist/starmaker-top-songs/294",
    "source_name": "playlist",
    "song_title": "Billie Eilish",
    "artist": "Points",
    "recordings_raw": "78K recordings",
    "recordings_num": 78000
  },
  {
    "scraped_at": "2026-07-21T20:18:25+00:00",
    "source_url": "https://www.starmakerstudios.com/en/songs",
    "source_name": "songs",
    "song_title": "Neha Kakkar",
    "artist": "Points",
    "recordings_raw": "68K recordings",
    "recordings_num": 68000
  },
  {
    "scraped_at": "2026-07-21T20:18:25+00:00",
    "source_url": "https://www.starmakerstudios.com/en/songs",
    "source_name": "songs",
    "song_title": "Elvis Presley",
    "artist": "Points",
    "recordings_raw": "59K recordings",
    "recordings_num": 59000
  },
  {
    "scraped_at": "2026-07-21T20:18:25+00:00",
    "source_url": "https://www.starmakerstudios.com/en/songs",
    "source_name": "songs",
    "song_title": "Auli'i Cravalho",
    "artist": "Points",
    "recordings_raw": "57K recordings",
    "recordings_num": 57000
  },
  {
    "scraped_at": "2026-07-21T20:18:25+00:00",
    "source_url": "https://www.starmakerstudios.com/en/songs",
    "source_name": "songs",
    "song_title": "Zara",
    "artist": "Points",
    "recordings_raw": "47K recordings",
    "recordings_num": 47000
  },
  {
    "scraped_at": "2026-07-21T20:18:25+00:00",
    "source_url": "https://www.starmakerstudios.com/en/songs",
    "source_name": "songs",
    "song_title": "Garth Brooks",
    "artist": "Points",
    "recordings_raw": "43K recordings",
    "recordings_num": 43000
  },
  {
    "scraped_at": "2026-07-21T20:18:25+00:00",
    "source_url": "https://www.starmakerstudios.com/en/songs",
    "source_name": "songs",
    "song_title": "Sofia the First",
    "artist": "Points",
    "recordings_raw": "42K recordings",
    "recordings_num": 42000
  },
  {
    "scraped_at": "2026-07-21T20:18:25+00:00",
    "source_url": "https://www.starmakerstudios.com/en/songs",
    "source_name": "songs",
    "song_title": "Bee Gees",
    "artist": "Points",
    "recordings_raw": "40K recordings",
    "recordings_num": 40000
  },
  {
    "scraped_at": "2026-07-21T20:18:25+00:00",
    "source_url": "https://www.starmakerstudios.com/en/songs",
    "source_name": "songs",
    "song_title": "Mariah Carey",
    "artist": "Points",
    "recordings_raw": "27K recordings",
    "recordings_num": 27000
  },
  {
    "scraped_at": "2026-07-21T20:18:27+00:00",
    "source_url": "https://www.starmakerstudios.com/playlist/%E6%9C%AC%E5%91%A8us%E7%86%B1%E9%96%80100/1357",
    "source_name": "playlist",
    "song_title": "Michael Jackson",
    "artist": "Points",
    "recordings_raw": "22K recordings",
    "recordings_num": 22000
  },
  {
    "scraped_at": "2026-07-21T20:18:25+00:00",
    "source_url": "https://www.starmakerstudios.com/en/songs",
    "source_name": "songs",
    "song_title": "Cranberries (크랜베리스)",
    "artist": "Points",
    "recordings_raw": "22K recordings",
    "recordings_num": 22000
  },
  {
    "scraped_at": "2026-07-21T20:18:27+00:00",
    "source_url": "https://www.starmakerstudios.com/playlist/%E6%9C%AC%E5%91%A8us%E7%86%B1%E9%96%80100/1357",
    "source_name": "playlist",
    "song_title": "Oliver Tree",
    "artist": "Points",
    "recordings_raw": "16K recordings",
    "recordings_num": 16000
  },
  {
    "scraped_at": "2026-07-21T20:18:25+00:00",
    "source_url": "https://www.starmakerstudios.com/en/songs",
    "source_name": "songs",
    "song_title": "Imran Mahmudul",
    "artist": "Points",
    "recordings_raw": "14K recordings",
    "recordings_num": 14000
  },
  {
    "scraped_at": "2026-07-21T20:18:25+00:00",
    "source_url": "https://www.starmakerstudios.com/en/songs",
    "source_name": "songs",
    "song_title": "Muni Long",
    "artist": "Points",
    "recordings_raw": "14K recordings",
    "recordings_num": 14000
  },
  {
    "scraped_at": "2026-07-21T20:18:25+00:00",
    "source_url": "https://www.starmakerstudios.com/en/songs",
    "source_name": "songs",
    "song_title": "Tim McGraw",
    "artist": "Points",
    "recordings_raw": "14K recordings",
    "recordings_num": 14000
  },
  {
    "scraped_at": "2026-07-21T20:18:25+00:00",
    "source_url": "https://www.starmakerstudios.com/en/songs",
    "source_name": "songs",
    "song_title": "Bini",
    "artist": "Points",
    "recordings_raw": "13K recordings",
    "recordings_num": 13000
  },
  {
    "scraped_at": "2026-07-21T20:18:25+00:00",
    "source_url": "https://www.starmakerstudios.com/en/songs",
    "source_name": "songs",
    "song_title": "Simpal Kharel",
    "artist": "Points",
    "recordings_raw": "12K recordings",
    "recordings_num": 12000
  },
  {
    "scraped_at": "2026-07-21T20:18:25+00:00",
    "source_url": "https://www.starmakerstudios.com/en/songs",
    "source_name": "songs",
    "song_title": "Jack Black",
    "artist": "Points",
    "recordings_raw": "11K recordings",
    "recordings_num": 11000
  },
  {
    "scraped_at": "2026-07-21T20:18:25+00:00",
    "source_url": "https://www.starmakerstudios.com/en/songs",
    "source_name": "songs",
    "song_title": "James Arthur",
    "artist": "Points",
    "recordings_raw": "10K recordings",
    "recordings_num": 10000
  },
  {
    "scraped_at": "2026-07-21T20:18:25+00:00",
    "source_url": "https://www.starmakerstudios.com/en/songs",
    "source_name": "songs",
    "song_title": "Alex Warren",
    "artist": "Points",
    "recordings_raw": "9K recordings",
    "recordings_num": 9000
  },
  {
    "scraped_at": "2026-07-21T20:18:25+00:00",
    "source_url": "https://www.starmakerstudios.com/en/songs",
    "source_name": "songs",
    "song_title": "Keyshia Cole",
    "artist": "Points",
    "recordings_raw": "8K recordings",
    "recordings_num": 8000
  },
  {
    "scraped_at": "2026-07-21T20:18:25+00:00",
    "source_url": "https://www.starmakerstudios.com/en/songs",
    "source_name": "songs",
    "song_title": "Adie",
    "artist": "Points",
    "recordings_raw": "8K recordings",
    "recordings_num": 8000
  },
  {
    "scraped_at": "2026-07-21T20:18:25+00:00",
    "source_url": "https://www.starmakerstudios.com/en/songs",
    "source_name": "songs",
    "song_title": "Chris Grey",
    "artist": "Points",
    "recordings_raw": "7K recordings",
    "recordings_num": 7000
  },
  {
    "scraped_at": "2026-07-21T20:18:25+00:00",
    "source_url": "https://www.starmakerstudios.com/en/songs",
    "source_name": "songs",
    "song_title": "Gooseworx",
    "artist": "Points",
    "recordings_raw": "7K recordings",
    "recordings_num": 7000
  },
  {
    "scraped_at": "2026-07-21T20:18:25+00:00",
    "source_url": "https://www.starmakerstudios.com/en/songs",
    "source_name": "songs",
    "song_title": "KATSEYE",
    "artist": "Points",
    "recordings_raw": "6K recordings",
    "recordings_num": 6000
  },
  {
    "scraped_at": "2026-07-21T20:18:25+00:00",
    "source_url": "https://www.starmakerstudios.com/en/songs",
    "source_name": "songs",
    "song_title": "Moira Dela Torre",
    "artist": "Points",
    "recordings_raw": "6K recordings",
    "recordings_num": 6000
  },
  {
    "scraped_at": "2026-07-21T20:18:25+00:00",
    "source_url": "https://www.starmakerstudios.com/en/songs",
    "source_name": "songs",
    "song_title": "Blake Shelton",
    "artist": "Points",
    "recordings_raw": "6K recordings",
    "recordings_num": 6000
  },
  {
    "scraped_at": "2026-07-21T20:18:25+00:00",
    "source_url": "https://www.starmakerstudios.com/en/songs",
    "source_name": "songs",
    "song_title": "Christina Perri",
    "artist": "Points",
    "recordings_raw": "6K recordings",
    "recordings_num": 6000
  },
  {
    "scraped_at": "2026-07-21T20:18:25+00:00",
    "source_url": "https://www.starmakerstudios.com/en/songs",
    "source_name": "songs",
    "song_title": "Atif Aslam",
    "artist": "Points",
    "recordings_raw": "6K recordings",
    "recordings_num": 6000
  },
  {
    "scraped_at": "2026-07-21T20:18:25+00:00",
    "source_url": "https://www.starmakerstudios.com/en/songs",
    "source_name": "songs",
    "song_title": "The Who",
    "artist": "Points",
    "recordings_raw": "6K recordings",
    "recordings_num": 6000
  },
  {
    "scraped_at": "2026-07-21T20:18:25+00:00",
    "source_url": "https://www.starmakerstudios.com/en/songs",
    "source_name": "songs",
    "song_title": "Victorious",
    "artist": "Points",
    "recordings_raw": "5K recordings",
    "recordings_num": 5000
  },
  {
    "scraped_at": "2026-07-21T20:18:25+00:00",
    "source_url": "https://www.starmakerstudios.com/en/songs",
    "source_name": "songs",
    "song_title": "Gracie Abrams",
    "artist": "Points",
    "recordings_raw": "4K recordings",
    "recordings_num": 4000
  },
  {
    "scraped_at": "2026-07-21T20:18:25+00:00",
    "source_url": "https://www.starmakerstudios.com/en/songs",
    "source_name": "songs",
    "song_title": "Connie Francis",
    "artist": "Points",
    "recordings_raw": "4K recordings",
    "recordings_num": 4000
  },
  {
    "scraped_at": "2026-07-21T20:18:25+00:00",
    "source_url": "https://www.starmakerstudios.com/en/songs",
    "source_name": "songs",
    "song_title": "Blake Roman/Sam Haft/Andrew Underberg",
    "artist": "Points",
    "recordings_raw": "4K recordings",
    "recordings_num": 4000
  },
  {
    "scraped_at": "2026-07-21T20:18:25+00:00",
    "source_url": "https://www.starmakerstudios.com/en/songs",
    "source_name": "songs",
    "song_title": "George Strait",
    "artist": "Points",
    "recordings_raw": "4K recordings",
    "recordings_num": 4000
  },
  {
    "scraped_at": "2026-07-21T20:18:27+00:00",
    "source_url": "https://www.starmakerstudios.com/playlist/%E6%9C%AC%E5%91%A8us%E7%86%B1%E9%96%80100/1357",
    "source_name": "playlist",
    "song_title": "LE SSERAFIM/ILLIT/KATSEYE",
    "artist": "Points",
    "recordings_raw": "4K recordings",
    "recordings_num": 4000
  },
  {
    "scraped_at": "2026-07-21T20:18:25+00:00",
    "source_url": "https://www.starmakerstudios.com/en/songs",
    "source_name": "songs",
    "song_title": "Sabina Yasmin",
    "artist": "Points",
    "recordings_raw": "3K recordings",
    "recordings_num": 3000
  },
  {
    "scraped_at": "2026-07-21T20:18:25+00:00",
    "source_url": "https://www.starmakerstudios.com/en/songs",
    "source_name": "songs",
    "song_title": "Slander/Dylan Matthew",
    "artist": "Points",
    "recordings_raw": "3K recordings",
    "recordings_num": 3000
  },
  {
    "scraped_at": "2026-07-21T20:18:25+00:00",
    "source_url": "https://www.starmakerstudios.com/en/songs",
    "source_name": "songs",
    "song_title": "Ashe",
    "artist": "Moral Of The Story",
    "recordings_raw": "3K recordings",
    "recordings_num": 3000
  },
  {
    "scraped_at": "2026-07-21T20:18:27+00:00",
    "source_url": "https://www.starmakerstudios.com/playlist/%E6%9C%AC%E5%91%A8us%E7%86%B1%E9%96%80100/1357",
    "source_name": "playlist",
    "song_title": "Oliver Tree/Robin Schulz",
    "artist": "Points",
    "recordings_raw": "3K recordings",
    "recordings_num": 3000
  },
  {
    "scraped_at": "2026-07-21T20:18:25+00:00",
    "source_url": "https://www.starmakerstudios.com/en/songs",
    "source_name": "songs",
    "song_title": "Ziv Zaifman/Hugh Jackman/Michelle Williams",
    "artist": "Points",
    "recordings_raw": "2K recordings",
    "recordings_num": 2000
  },
  {
    "scraped_at": "2026-07-21T20:18:25+00:00",
    "source_url": "https://www.starmakerstudios.com/en/songs",
    "source_name": "songs",
    "song_title": "Aditya Rikhari",
    "artist": "Points",
    "recordings_raw": "2K recordings",
    "recordings_num": 2000
  },
  {
    "scraped_at": "2026-07-21T20:18:25+00:00",
    "source_url": "https://www.starmakerstudios.com/en/songs",
    "source_name": "songs",
    "song_title": "OR3O/Lizzie Freeman",
    "artist": "Points",
    "recordings_raw": "2K recordings",
    "recordings_num": 2000
  },
  {
    "scraped_at": "2026-07-21T20:18:27+00:00",
    "source_url": "https://www.starmakerstudios.com/playlist/%E6%9C%AC%E5%91%A8us%E7%86%B1%E9%96%80100/1357",
    "source_name": "playlist",
    "song_title": "IShowSpeed",
    "artist": "World Cup",
    "recordings_raw": "2K recordings",
    "recordings_num": 2000
  },
  {
    "scraped_at": "2026-07-21T20:18:25+00:00",
    "source_url": "https://www.starmakerstudios.com/en/songs",
    "source_name": "songs",
    "song_title": "阿拉蕾读英文绘本",
    "artist": "Points",
    "recordings_raw": "1K recordings",
    "recordings_num": 1000
  },
  {
    "scraped_at": "2026-07-21T20:18:25+00:00",
    "source_url": "https://www.starmakerstudios.com/en/songs",
    "source_name": "songs",
    "song_title": "Ruth B.",
    "artist": "Points",
    "recordings_raw": "1K recordings",
    "recordings_num": 1000
  },
  {
    "scraped_at": "2026-07-21T20:18:25+00:00",
    "source_url": "https://www.starmakerstudios.com/en/songs",
    "source_name": "songs",
    "song_title": "Huntrix",
    "artist": "Golden (KPop Demon Hunters) - Huntrix Piano Version NJP",
    "recordings_raw": "1K recordings",
    "recordings_num": 1000
  },
  {
    "scraped_at": "2026-07-21T20:18:25+00:00",
    "source_url": "https://www.starmakerstudios.com/en/songs",
    "source_name": "songs",
    "song_title": "Red Illusions",
    "artist": "Points",
    "recordings_raw": "1K recordings",
    "recordings_num": 1000
  },
  {
    "scraped_at": "2026-07-21T20:18:25+00:00",
    "source_url": "https://www.starmakerstudios.com/en/songs",
    "source_name": "songs",
    "song_title": "AUDREY NUNA/EJAE/HUNTR/X/KPop Demon Hunters Cast",
    "artist": "Points",
    "recordings_raw": "1K recordings",
    "recordings_num": 1000
  },
  {
    "scraped_at": "2026-07-21T20:18:25+00:00",
    "source_url": "https://www.starmakerstudios.com/en/songs",
    "source_name": "songs",
    "song_title": "Post Malone",
    "artist": "Points",
    "recordings_raw": "1K recordings",
    "recordings_num": 1000
  },
  {
    "scraped_at": "2026-07-21T20:18:25+00:00",
    "source_url": "https://www.starmakerstudios.com/en/songs",
    "source_name": "songs",
    "song_title": "hazbin hotel/Keith David/Lilli Cooper/Kimiko Glenn",
    "artist": "Points",
    "recordings_raw": "1K recordings",
    "recordings_num": 1000
  },
  {
    "scraped_at": "2026-07-21T20:18:25+00:00",
    "source_url": "https://www.starmakerstudios.com/en/songs",
    "source_name": "songs",
    "song_title": "fitterkarma",
    "artist": "Points",
    "recordings_raw": "1K recordings",
    "recordings_num": 1000
  },
  {
    "scraped_at": "2026-07-21T20:18:25+00:00",
    "source_url": "https://www.starmakerstudios.com/en/songs",
    "source_name": "songs",
    "song_title": "JULIA WOLF",
    "artist": "Points",
    "recordings_raw": "1K recordings",
    "recordings_num": 1000
  },
  {
    "scraped_at": "2026-07-21T20:18:25+00:00",
    "source_url": "https://www.starmakerstudios.com/en/songs",
    "source_name": "songs",
    "song_title": "Glen Campbell",
    "artist": "Points",
    "recordings_raw": "997 recordings",
    "recordings_num": 997
  },
  {
    "scraped_at": "2026-07-21T20:18:27+00:00",
    "source_url": "https://www.starmakerstudios.com/playlist/%E6%9C%AC%E5%91%A8us%E7%86%B1%E9%96%80100/1357",
    "source_name": "playlist",
    "song_title": "Huntrix",
    "artist": "G0LDEN",
    "recordings_raw": "963 recordings",
    "recordings_num": 963
  },
  {
    "scraped_at": "2026-07-21T20:18:25+00:00",
    "source_url": "https://www.starmakerstudios.com/en/songs",
    "source_name": "songs",
    "song_title": "Marina/The Diamonds",
    "artist": "Points",
    "recordings_raw": "935 recordings",
    "recordings_num": 935
  },
  {
    "scraped_at": "2026-07-21T20:18:25+00:00",
    "source_url": "https://www.starmakerstudios.com/en/songs",
    "source_name": "songs",
    "song_title": "Martin Garrix",
    "artist": "Points",
    "recordings_raw": "657 recordings",
    "recordings_num": 657
  },
  {
    "scraped_at": "2026-07-21T20:18:27+00:00",
    "source_url": "https://www.starmakerstudios.com/playlist/%E6%9C%AC%E5%91%A8us%E7%86%B1%E9%96%80100/1357",
    "source_name": "playlist",
    "song_title": "Shakira/Burna Boy",
    "artist": "Points",
    "recordings_raw": "644 recordings",
    "recordings_num": 644
  },
  {
    "scraped_at": "2026-07-21T20:18:25+00:00",
    "source_url": "https://www.starmakerstudios.com/en/songs",
    "source_name": "songs",
    "song_title": "Agtverse",
    "artist": "Points",
    "recordings_raw": "599 recordings",
    "recordings_num": 599
  },
  {
    "scraped_at": "2026-07-21T20:18:25+00:00",
    "source_url": "https://www.starmakerstudios.com/en/songs",
    "source_name": "songs",
    "song_title": "Tyler, The Creator/Lola Young",
    "artist": "Points",
    "recordings_raw": "554 recordings",
    "recordings_num": 554
  },
  {
    "scraped_at": "2026-07-21T20:18:25+00:00",
    "source_url": "https://www.starmakerstudios.com/en/songs",
    "source_name": "songs",
    "song_title": "The Living Tombstone",
    "artist": "Points",
    "recordings_raw": "512 recordings",
    "recordings_num": 512
  },
  {
    "scraped_at": "2026-07-21T20:18:25+00:00",
    "source_url": "https://www.starmakerstudios.com/en/songs",
    "source_name": "songs",
    "song_title": "The Greatest Showman Cast",
    "artist": "Rewrite The Stars",
    "recordings_raw": "464 recordings",
    "recordings_num": 464
  },
  {
    "scraped_at": "2026-07-21T20:18:25+00:00",
    "source_url": "https://www.starmakerstudios.com/en/songs",
    "source_name": "songs",
    "song_title": "Afusic",
    "artist": "Points",
    "recordings_raw": "440 recordings",
    "recordings_num": 440
  },
  {
    "scraped_at": "2026-07-21T20:18:25+00:00",
    "source_url": "https://www.starmakerstudios.com/en/songs",
    "source_name": "songs",
    "song_title": "Inanimate Insanity",
    "artist": "The Future Is So Yesterday",
    "recordings_raw": "421 recordings",
    "recordings_num": 421
  },
  {
    "scraped_at": "2026-07-21T20:18:25+00:00",
    "source_url": "https://www.starmakerstudios.com/en/songs",
    "source_name": "songs",
    "song_title": "Patti LaBelle",
    "artist": "If You Asked Me To",
    "recordings_raw": "400 recordings",
    "recordings_num": 400
  },
  {
    "scraped_at": "2026-07-21T20:18:25+00:00",
    "source_url": "https://www.starmakerstudios.com/en/songs",
    "source_name": "songs",
    "song_title": "Dove Cameron",
    "artist": "Points",
    "recordings_raw": "399 recordings",
    "recordings_num": 399
  },
  {
    "scraped_at": "2026-07-21T20:18:25+00:00",
    "source_url": "https://www.starmakerstudios.com/en/songs",
    "source_name": "songs",
    "song_title": "SB19",
    "artist": "Points",
    "recordings_raw": "258 recordings",
    "recordings_num": 258
  },
  {
    "scraped_at": "2026-07-21T20:18:27+00:00",
    "source_url": "https://www.starmakerstudios.com/playlist/%E6%9C%AC%E5%91%A8us%E7%86%B1%E9%96%80100/1357",
    "source_name": "playlist",
    "song_title": "KitschKrieg/Blumengarten/shirin david",
    "artist": "Points",
    "recordings_raw": "208 recordings",
    "recordings_num": 208
  },
  {
    "scraped_at": "2026-07-21T20:18:25+00:00",
    "source_url": "https://www.starmakerstudios.com/en/songs",
    "source_name": "songs",
    "song_title": "KATSEYE",
    "artist": "PINKY UP(Clean Edit)(Clean)",
    "recordings_raw": "155 recordings",
    "recordings_num": 155
  },
  {
    "scraped_at": "2026-07-21T20:18:27+00:00",
    "source_url": "https://www.starmakerstudios.com/playlist/%E6%9C%AC%E5%91%A8us%E7%86%B1%E9%96%80100/1357",
    "source_name": "playlist",
    "song_title": "Shakira",
    "artist": "Points",
    "recordings_raw": "144 recordings",
    "recordings_num": 144
  },
  {
    "scraped_at": "2026-07-21T20:18:25+00:00",
    "source_url": "https://www.starmakerstudios.com/en/songs",
    "source_name": "songs",
    "song_title": "Chicky Milky",
    "artist": "Points",
    "recordings_raw": "137 recordings",
    "recordings_num": 137
  },
  {
    "scraped_at": "2026-07-21T20:18:27+00:00",
    "source_url": "https://www.starmakerstudios.com/playlist/%E6%9C%AC%E5%91%A8us%E7%86%B1%E9%96%80100/1357",
    "source_name": "playlist",
    "song_title": "Mauvais djo",
    "artist": "Points",
    "recordings_raw": "80 recordings",
    "recordings_num": 80
  },
  {
    "scraped_at": "2026-07-21T20:18:25+00:00",
    "source_url": "https://www.starmakerstudios.com/en/songs",
    "source_name": "songs",
    "song_title": "Super Simple Songs",
    "artist": "Points",
    "recordings_raw": "32 recordings",
    "recordings_num": 32
  },
  {
    "scraped_at": "2026-07-21T20:18:25+00:00",
    "source_url": "https://www.starmakerstudios.com/en/songs",
    "source_name": "songs",
    "song_title": "BFDI Music",
    "artist": "Points",
    "recordings_raw": "32 recordings",
    "recordings_num": 32
  },
  {
    "scraped_at": "2026-07-21T20:18:25+00:00",
    "source_url": "https://www.starmakerstudios.com/en/songs",
    "source_name": "songs",
    "song_title": "Kpop Demon Hunters",
    "artist": "Points",
    "recordings_raw": "23 recordings",
    "recordings_num": 23
  }
]