[
  {
    "scraped_at": "2026-04-11T10:41:05+00:00",
    "source_url": "https://www.starmakerstudios.com/en/playlist/starmaker-top-songs/294",
    "source_name": "playlist",
    "song_title": "John Legend",
    "artist": "Points",
    "recordings_raw": "791K recordings",
    "recordings_num": 791000
  },
  {
    "scraped_at": "2026-04-11T10:41:05+00:00",
    "source_url": "https://www.starmakerstudios.com/en/playlist/starmaker-top-songs/294",
    "source_name": "playlist",
    "song_title": "Ed Sheeran",
    "artist": "Points",
    "recordings_raw": "660K recordings",
    "recordings_num": 660000
  },
  {
    "scraped_at": "2026-04-11T10:41:05+00:00",
    "source_url": "https://www.starmakerstudios.com/en/playlist/starmaker-top-songs/294",
    "source_name": "playlist",
    "song_title": "Ellie Goulding",
    "artist": "Points",
    "recordings_raw": "402K recordings",
    "recordings_num": 402000
  },
  {
    "scraped_at": "2026-04-11T10:41:05+00:00",
    "source_url": "https://www.starmakerstudios.com/en/playlist/starmaker-top-songs/294",
    "source_name": "playlist",
    "song_title": "Charlie Puth",
    "artist": "Points",
    "recordings_raw": "348K recordings",
    "recordings_num": 348000
  },
  {
    "scraped_at": "2026-04-11T10:41:05+00:00",
    "source_url": "https://www.starmakerstudios.com/en/playlist/starmaker-top-songs/294",
    "source_name": "playlist",
    "song_title": "Shawn Mendes",
    "artist": "Points",
    "recordings_raw": "228K recordings",
    "recordings_num": 228000
  },
  {
    "scraped_at": "2026-04-11T10:41:06+00:00",
    "source_url": "https://www.starmakerstudios.com/en/songs",
    "source_name": "songs",
    "song_title": "Dan Hill",
    "artist": "Points",
    "recordings_raw": "223K recordings",
    "recordings_num": 223000
  },
  {
    "scraped_at": "2026-04-11T10:41:05+00:00",
    "source_url": "https://www.starmakerstudios.com/en/playlist/starmaker-top-songs/294",
    "source_name": "playlist",
    "song_title": "Bruno Mars",
    "artist": "Points",
    "recordings_raw": "164K recordings",
    "recordings_num": 164000
  },
  {
    "scraped_at": "2026-04-11T10:41:05+00:00",
    "source_url": "https://www.starmakerstudios.com/en/playlist/starmaker-top-songs/294",
    "source_name": "playlist",
    "song_title": "Lewis Capaldi",
    "artist": "Points",
    "recordings_raw": "154K recordings",
    "recordings_num": 154000
  },
  {
    "scraped_at": "2026-04-11T10:41:05+00:00",
    "source_url": "https://www.starmakerstudios.com/en/playlist/starmaker-top-songs/294",
    "source_name": "playlist",
    "song_title": "Hozier",
    "artist": "Points",
    "recordings_raw": "80K recordings",
    "recordings_num": 80000
  },
  {
    "scraped_at": "2026-04-11T10:41:05+00:00",
    "source_url": "https://www.starmakerstudios.com/en/playlist/starmaker-top-songs/294",
    "source_name": "playlist",
    "song_title": "Billie Eilish",
    "artist": "Points",
    "recordings_raw": "73K recordings",
    "recordings_num": 73000
  },
  {
    "scraped_at": "2026-04-11T10:41:06+00:00",
    "source_url": "https://www.starmakerstudios.com/en/songs",
    "source_name": "songs",
    "song_title": "Auli'i Cravalho",
    "artist": "Points",
    "recordings_raw": "57K recordings",
    "recordings_num": 57000
  },
  {
    "scraped_at": "2026-04-11T10:41:06+00:00",
    "source_url": "https://www.starmakerstudios.com/en/songs",
    "source_name": "songs",
    "song_title": "Britney Spears",
    "artist": "Points",
    "recordings_raw": "51K recordings",
    "recordings_num": 51000
  },
  {
    "scraped_at": "2026-04-11T10:41:06+00:00",
    "source_url": "https://www.starmakerstudios.com/en/songs",
    "source_name": "songs",
    "song_title": "Julia Michaels",
    "artist": "Points",
    "recordings_raw": "35K recordings",
    "recordings_num": 35000
  },
  {
    "scraped_at": "2026-04-11T10:41:06+00:00",
    "source_url": "https://www.starmakerstudios.com/en/songs",
    "source_name": "songs",
    "song_title": "Christina Aguilera/A Great Big World",
    "artist": "Points",
    "recordings_raw": "33K recordings",
    "recordings_num": 33000
  },
  {
    "scraped_at": "2026-04-11T10:41:06+00:00",
    "source_url": "https://www.starmakerstudios.com/en/songs",
    "source_name": "songs",
    "song_title": "Gigi Perez",
    "artist": "Points",
    "recordings_raw": "30K recordings",
    "recordings_num": 30000
  },
  {
    "scraped_at": "2026-04-11T10:41:06+00:00",
    "source_url": "https://www.starmakerstudios.com/en/songs",
    "source_name": "songs",
    "song_title": "JVKE",
    "artist": "Points",
    "recordings_raw": "19K recordings",
    "recordings_num": 19000
  },
  {
    "scraped_at": "2026-04-11T10:41:08+00:00",
    "source_url": "https://www.starmakerstudios.com/playlist/%E6%9C%AC%E5%91%A8us%E7%86%B1%E9%96%80100/1357",
    "source_name": "playlist",
    "song_title": "George Benson/David Slater/James Ingram",
    "artist": "Points",
    "recordings_raw": "7K recordings",
    "recordings_num": 7000
  },
  {
    "scraped_at": "2026-04-11T10:41:06+00:00",
    "source_url": "https://www.starmakerstudios.com/en/songs",
    "source_name": "songs",
    "song_title": "Heathers",
    "artist": "Points",
    "recordings_raw": "3K recordings",
    "recordings_num": 3000
  },
  {
    "scraped_at": "2026-04-11T10:41:06+00:00",
    "source_url": "https://www.starmakerstudios.com/en/songs",
    "source_name": "songs",
    "song_title": "Olivia Rodrigo",
    "artist": "Points",
    "recordings_raw": "3K recordings",
    "recordings_num": 3000
  },
  {
    "scraped_at": "2026-04-11T10:41:06+00:00",
    "source_url": "https://www.starmakerstudios.com/en/songs",
    "source_name": "songs",
    "song_title": "Victoria Monét",
    "artist": "Points",
    "recordings_raw": "3K recordings",
    "recordings_num": 3000
  },
  {
    "scraped_at": "2026-04-11T10:41:06+00:00",
    "source_url": "https://www.starmakerstudios.com/en/songs",
    "source_name": "songs",
    "song_title": "Alanis Morissette",
    "artist": "Points",
    "recordings_raw": "3K recordings",
    "recordings_num": 3000
  },
  {
    "scraped_at": "2026-04-11T10:41:06+00:00",
    "source_url": "https://www.starmakerstudios.com/en/songs",
    "source_name": "songs",
    "song_title": "Danny Elfman",
    "artist": "Points",
    "recordings_raw": "2K recordings",
    "recordings_num": 2000
  },
  {
    "scraped_at": "2026-04-11T10:41:06+00:00",
    "source_url": "https://www.starmakerstudios.com/en/songs",
    "source_name": "songs",
    "song_title": "Halsey",
    "artist": "Points",
    "recordings_raw": "2K recordings",
    "recordings_num": 2000
  },
  {
    "scraped_at": "2026-04-11T10:41:06+00:00",
    "source_url": "https://www.starmakerstudios.com/en/songs",
    "source_name": "songs",
    "song_title": "The Fray",
    "artist": "Points",
    "recordings_raw": "2K recordings",
    "recordings_num": 2000
  },
  {
    "scraped_at": "2026-04-11T10:41:06+00:00",
    "source_url": "https://www.starmakerstudios.com/en/songs",
    "source_name": "songs",
    "song_title": "Shinedown",
    "artist": "Points",
    "recordings_raw": "1K recordings",
    "recordings_num": 1000
  },
  {
    "scraped_at": "2026-04-11T10:41:08+00:00",
    "source_url": "https://www.starmakerstudios.com/playlist/%E6%9C%AC%E5%91%A8us%E7%86%B1%E9%96%80100/1357",
    "source_name": "playlist",
    "song_title": "Tame Impala/JENNIE",
    "artist": "Points",
    "recordings_raw": "1K recordings",
    "recordings_num": 1000
  },
  {
    "scraped_at": "2026-04-11T10:41:06+00:00",
    "source_url": "https://www.starmakerstudios.com/en/songs",
    "source_name": "songs",
    "song_title": "USA National Anthem",
    "artist": "Points",
    "recordings_raw": "496 recordings",
    "recordings_num": 496
  },
  {
    "scraped_at": "2026-04-11T10:41:06+00:00",
    "source_url": "https://www.starmakerstudios.com/en/songs",
    "source_name": "songs",
    "song_title": "Adventure Time/Olivia Olson",
    "artist": "Points",
    "recordings_raw": "441 recordings",
    "recordings_num": 441
  },
  {
    "scraped_at": "2026-04-11T10:41:08+00:00",
    "source_url": "https://www.starmakerstudios.com/playlist/%E6%9C%AC%E5%91%A8us%E7%86%B1%E9%96%80100/1357",
    "source_name": "playlist",
    "song_title": "Miami XO",
    "artist": "Points",
    "recordings_raw": "53 recordings",
    "recordings_num": 53
  },
  {
    "scraped_at": "2026-04-11T10:41:08+00:00",
    "source_url": "https://www.starmakerstudios.com/playlist/%E6%9C%AC%E5%91%A8us%E7%86%B1%E9%96%80100/1357",
    "source_name": "playlist",
    "song_title": "Scylla",
    "artist": "Points",
    "recordings_raw": "41 recordings",
    "recordings_num": 41
  },
  {
    "scraped_at": "2026-04-11T10:41:06+00:00",
    "source_url": "https://www.starmakerstudios.com/en/songs",
    "source_name": "songs",
    "song_title": "Nu Shooz",
    "artist": "I Can't Wait",
    "recordings_raw": "25 recordings",
    "recordings_num": 25
  },
  {
    "scraped_at": "2026-04-11T10:41:08+00:00",
    "source_url": "https://www.starmakerstudios.com/playlist/%E6%9C%AC%E5%91%A8us%E7%86%B1%E9%96%80100/1357",
    "source_name": "playlist",
    "song_title": "A Tuân",
    "artist": "Points",
    "recordings_raw": "22 recordings",
    "recordings_num": 22
  },
  {
    "scraped_at": "2026-04-11T10:41:08+00:00",
    "source_url": "https://www.starmakerstudios.com/playlist/%E6%9C%AC%E5%91%A8us%E7%86%B1%E9%96%80100/1357",
    "source_name": "playlist",
    "song_title": "Temper City",
    "artist": "Points",
    "recordings_raw": "14 recordings",
    "recordings_num": 14
  },
  {
    "scraped_at": "2026-04-11T10:41:08+00:00",
    "source_url": "https://www.starmakerstudios.com/playlist/%E6%9C%AC%E5%91%A8us%E7%86%B1%E9%96%80100/1357",
    "source_name": "playlist",
    "song_title": "BossMan Dlow",
    "artist": "Points",
    "recordings_raw": "3 recordings",
    "recordings_num": 3
  },
  {
    "scraped_at": "2026-04-11T10:41:08+00:00",
    "source_url": "https://www.starmakerstudios.com/playlist/%E6%9C%AC%E5%91%A8us%E7%86%B1%E9%96%80100/1357",
    "source_name": "playlist",
    "song_title": "Nunslaughter",
    "artist": "Pyre",
    "recordings_raw": "1 recordings",
    "recordings_num": 1
  },
  {
    "scraped_at": "2026-04-11T10:41:08+00:00",
    "source_url": "https://www.starmakerstudios.com/playlist/%E6%9C%AC%E5%91%A8us%E7%86%B1%E9%96%80100/1357",
    "source_name": "playlist",
    "song_title": "Voi",
    "artist": "blissful lights",
    "recordings_raw": "0 recordings",
    "recordings_num": 0
  },
  {
    "scraped_at": "2026-04-11T10:41:08+00:00",
    "source_url": "https://www.starmakerstudios.com/playlist/%E6%9C%AC%E5%91%A8us%E7%86%B1%E9%96%80100/1357",
    "source_name": "playlist",
    "song_title": "Yehezkel Raz",
    "artist": "Ballerina",
    "recordings_raw": "0 recordings",
    "recordings_num": 0
  }
]