[
  {
    "song_title": "Lukas Graham",
    "artist": "Points",
    "source_name": "songs",
    "current_recordings": 140000,
    "previous_recordings": 52000,
    "growth": 88000,
    "hours_window": 24
  },
  {
    "song_title": "Lewis Capaldi",
    "artist": "Points",
    "source_name": "songs",
    "current_recordings": 210000,
    "previous_recordings": 154000,
    "growth": 56000,
    "hours_window": 24
  },
  {
    "song_title": "Michael Jackson",
    "artist": "Points",
    "source_name": "songs",
    "current_recordings": 25000,
    "previous_recordings": 22000,
    "growth": 3000,
    "hours_window": 24
  },
  {
    "song_title": "Oliver Tree",
    "artist": "Points",
    "source_name": "playlist",
    "current_recordings": 16000,
    "previous_recordings": 15000,
    "growth": 1000,
    "hours_window": 24
  },
  {
    "song_title": "Shakira/Burna Boy",
    "artist": "Points",
    "source_name": "playlist",
    "current_recordings": 634,
    "previous_recordings": 622,
    "growth": 12,
    "hours_window": 24
  },
  {
    "song_title": "KitschKrieg/Blumengarten/shirin david",
    "artist": "Points",
    "source_name": "playlist",
    "current_recordings": 201,
    "previous_recordings": 191,
    "growth": 10,
    "hours_window": 24
  },
  {
    "song_title": "Huntrix",
    "artist": "G0LDEN",
    "source_name": "playlist",
    "current_recordings": 963,
    "previous_recordings": 962,
    "growth": 1,
    "hours_window": 24
  },
  {
    "song_title": "Shakira",
    "artist": "Points",
    "source_name": "playlist",
    "current_recordings": 144,
    "previous_recordings": 143,
    "growth": 1,
    "hours_window": 24
  },
  {
    "song_title": "Mauvais djo",
    "artist": "Points",
    "source_name": "playlist",
    "current_recordings": 78,
    "previous_recordings": 77,
    "growth": 1,
    "hours_window": 24
  }
]