[
  {
    "song_title": "Lewis Capaldi",
    "artist": "Points",
    "source_name": "songs",
    "current_recordings": 205000,
    "previous_recordings": 154000,
    "growth": 51000,
    "hours_window": 24
  },
  {
    "song_title": "JVKE",
    "artist": "Points",
    "source_name": "songs",
    "current_recordings": 52000,
    "previous_recordings": 4000,
    "growth": 48000,
    "hours_window": 24
  },
  {
    "song_title": "Bts",
    "artist": "SWIM",
    "source_name": "playlist",
    "current_recordings": 584,
    "previous_recordings": 531,
    "growth": 53,
    "hours_window": 24
  },
  {
    "song_title": "Dominic Fike",
    "artist": "Points",
    "source_name": "playlist",
    "current_recordings": 601,
    "previous_recordings": 579,
    "growth": 22,
    "hours_window": 24
  },
  {
    "song_title": "Tame Impala",
    "artist": "Points",
    "source_name": "playlist",
    "current_recordings": 273,
    "previous_recordings": 267,
    "growth": 6,
    "hours_window": 24
  },
  {
    "song_title": "Kendrick Lamar/SZA",
    "artist": "luther (with sza)",
    "source_name": "playlist",
    "current_recordings": 835,
    "previous_recordings": 833,
    "growth": 2,
    "hours_window": 24
  }
]