[
  {
    "song_title": "Michael Jackson",
    "artist": "Points",
    "source_name": "songs",
    "current_recordings": 30000,
    "previous_recordings": 22000,
    "growth": 8000,
    "hours_window": 24
  },
  {
    "song_title": "KitschKrieg/Blumengarten/shirin david",
    "artist": "Points",
    "source_name": "playlist",
    "current_recordings": 151,
    "previous_recordings": 142,
    "growth": 9,
    "hours_window": 24
  },
  {
    "song_title": "Shakira/Burna Boy",
    "artist": "Points",
    "source_name": "playlist",
    "current_recordings": 588,
    "previous_recordings": 581,
    "growth": 7,
    "hours_window": 24
  },
  {
    "song_title": "Mauvais djo",
    "artist": "Points",
    "source_name": "playlist",
    "current_recordings": 71,
    "previous_recordings": 66,
    "growth": 5,
    "hours_window": 24
  },
  {
    "song_title": "Shakira",
    "artist": "Points",
    "source_name": "playlist",
    "current_recordings": 140,
    "previous_recordings": 138,
    "growth": 2,
    "hours_window": 24
  },
  {
    "song_title": "Huntrix",
    "artist": "G0LDEN",
    "source_name": "playlist",
    "current_recordings": 961,
    "previous_recordings": 960,
    "growth": 1,
    "hours_window": 24
  }
]