[
  {
    "song_title": "Lewis Capaldi",
    "artist": "Points",
    "source_name": "songs",
    "current_recordings": 295000,
    "previous_recordings": 154000,
    "growth": 141000,
    "hours_window": 24
  },
  {
    "song_title": "Rihanna",
    "artist": "Points",
    "source_name": "songs",
    "current_recordings": 107000,
    "previous_recordings": 13000,
    "growth": 94000,
    "hours_window": 24
  },
  {
    "song_title": "John Legend",
    "artist": "Points",
    "source_name": "playlist",
    "current_recordings": 792000,
    "previous_recordings": 791000,
    "growth": 1000,
    "hours_window": 24
  },
  {
    "song_title": "Billie Eilish",
    "artist": "Points",
    "source_name": "playlist",
    "current_recordings": 74000,
    "previous_recordings": 73000,
    "growth": 1000,
    "hours_window": 24
  },
  {
    "song_title": "Tame Impala",
    "artist": "Points",
    "source_name": "playlist",
    "current_recordings": 525,
    "previous_recordings": 511,
    "growth": 14,
    "hours_window": 24
  },
  {
    "song_title": "Kendrick Lamar/SZA",
    "artist": "Points",
    "source_name": "playlist",
    "current_recordings": 851,
    "previous_recordings": 849,
    "growth": 2,
    "hours_window": 24
  },
  {
    "song_title": "Omar Courtz",
    "artist": "Points",
    "source_name": "playlist",
    "current_recordings": 12,
    "previous_recordings": 11,
    "growth": 1,
    "hours_window": 24
  }
]