[
  {
    "song_title": "Tame Impala",
    "artist": "Points",
    "source_name": "playlist",
    "current_recordings": 998,
    "previous_recordings": 980,
    "growth": 18,
    "hours_window": 24
  },
  {
    "song_title": "SIENNA SPIRO",
    "artist": "Points",
    "source_name": "playlist",
    "current_recordings": 425,
    "previous_recordings": 414,
    "growth": 11,
    "hours_window": 24
  },
  {
    "song_title": "Daniel Caesar",
    "artist": "Points",
    "source_name": "playlist",
    "current_recordings": 236,
    "previous_recordings": 234,
    "growth": 2,
    "hours_window": 24
  },
  {
    "song_title": "Dexter/The Moonrocks",
    "artist": "Points",
    "source_name": "playlist",
    "current_recordings": 7,
    "previous_recordings": 5,
    "growth": 2,
    "hours_window": 24
  }
]